Modules/Sequential/DFF.v
// D flip-flop with asynchronous reset (V2001, V2005)
module DFF (
    output reg Q, nQ,
    input D, Clk, rst
);
    always @(posedge Clk, negedge rst) begin
        if (!rst) begin
            Q <= 1'b0;
        end else
        Q <= D;
        nQ <= ~Q;
    end
endmodule

module t_DFF;
    wire wire_Q, wire_nQ;
    reg reg_D, reg_Clk, reg_rst;
    DFF dff (wire_Q, wire_nQ, reg_D, reg_Clk, reg_rst);

    // Output Dump File
    initial begin
        $dumpfile("DFF.vcd");
        $dumpvars(0, t_DFF);
    end

    // Clock
    initial begin
            reg_Clk <= 0;
        forever begin
            #5 reg_Clk = ~reg_Clk;
        end
    end

    initial fork
        #0 reg_rst = 0;
        #2 reg_rst = 1;
        #87 reg_rst = 0;
        #92 reg_rst = 1;

        #10 reg_D = 1;
        #20 reg_D = 0;
        #30 reg_D = 0;
        #40 reg_D = 1;
        #50 reg_D = 0;
        #60 reg_D = 1;
        #70 reg_D = 0;
        #80 reg_D = 0;
        #90 reg_D = 1;
        #100 reg_D = 0;
    join
    initial #250 $finish;
endmodule

Modules/Sequential/JK_FF.v
`include "DFF.v";

module JK_FF (
    output reg Q, output nQ,
    input J, K, Clk
);
    assign nQ = ~Q;
    always @(posedge Clk) begin
        case ({J, K})
        2'b00: Q <= Q;
        2'b01: Q <= 1'b0;
        2'b10: Q <= 1'b1;
        2'b11: Q <= ~Q;
    endcase
    end
endmodule



module t_JK_FF;
    wire Q, nQ;
    reg J, K, Clk;
    JK_FF jkff(Q, nQ,J, K, Clk);
    initial begin
        #0 Clk <= 1'b0;
        forever begin
            #5 Clk <= ~Clk;
        end
    end

    initial begin
        $dumpfile("JK_FF.vcd");
        $dumpvars(0, t_JK_FF);
    end

    initial fork
		 #2 J = 1;
		 #2 K = 0;
		 
		 #22 J = 0;
		 #22 K = 1;
		 
		 #32 J = 0;
		 #32 K = 0;
		 
		 #42 J = 1;
		 #42 K = 1;
		 
		 
		 #52 J = 0;
		 #52 K = 0; 
		 
		 #62 J = 1;
		 #62 K = 1;
    join
    initial #200 $finish;
endmodule

Modules/Sequential/output/JK_FF.vcd
$date
	Wed Nov  6 00:54:10 2024
$end
$version
	Icarus Verilog
$end
$timescale
	1s
$end
$scope module t_JK_FF $end
$var wire 1 ! nQ $end
$var wire 1 " Q $end
$var reg 1 # Clk $end
$var reg 1 $ J $end
$var reg 1 % K $end
$scope module jkff $end
$var wire 1 # Clk $end
$var wire 1 $ J $end
$var wire 1 % K $end
$var wire 1 ! nQ $end
$var reg 1 " Q $end
$upscope $end
$upscope $end
$enddefinitions $end
$comment Show the parameter values. $end
$dumpall
$end
#0
$dumpvars
x%
x$
0#
x"
x!
$end
#2
1$
0%
#5
0!
1"
1#
#10
0#
#15
1#
#20
0#
#22
0$
1%
#25
1!
0"
1#
#30
0#
#32
0%
#35
1#
#40
0#
#42
1$
1%
#45
0!
1"
1#
#50
0#
#52
0$
0%
#55
1#
#60
0#
#62
1$
1%
#65
1!
0"
1#
#70
0#
#75
0!
1"
1#
#80
0#
#85
1!
0"
1#
#90
0#
#95
0!
1"
1#
#100
0#
#105
1!
0"
1#
#110
0#
#115
0!
1"
1#
#120
0#
#125
1!
0"
1#
#130
0#
#135
0!
1"
1#
#140
0#
#145
1!
0"
1#
#150
0#
#155
0!
1"
1#
#160
0#
#165
1!
0"
1#
#170
0#
#175
0!
1"
1#
#180
0#
#185
1!
0"
1#
#190
0#
#195
0!
1"
1#
