LabWork_LabAssignments/LabTest_13Nov/t_Problem_5_16_n.v
// Kazi Rifat Morshed
// 230220

module DFF (
    output reg Q,  // ------------ reg missed
    nQ,
    input D,
    Clk,
    rst
);
    always @(posedge Clk, negedge rst) begin
        if (!rst) begin
            Q  <= 1'b0;
            nQ <= 1'b1;  // ----------------- missed
        end else begin
            Q  <= D;
            nQ <= ~Q;
        end
    end
endmodule  // WORKS


module TFF_with_DFF (
    output Q,
    nQ,
    input  T,
    Clk,
    rst
);
    wire _T;
    assign _T = Q ^ T;
    DFF dff (
        Q,
        nQ,
        _T,
        Clk,
        rst
    );
endmodule  // WORKS

module JK_FF (
    output reg Q,
    output nQ,
    input J,
    K,
    Clk,
    reset
);
    always @(posedge Clk or posedge reset) begin
        if (reset) Q <= 0;
        else if (J & ~K) Q <= 1'b1;
        else if (~J & K) Q <= 1'b0;
        else if (J & K) Q <= ~Q;
    end
    // always @(posedge Clk) begin
    //     case ({
    //         J, K
    //     })
    //         2'b00: Q <= Q;
    //         2'b01: Q <= 1'b0;
    //         2'b10: Q <= 1'b1;
    //         2'b11: Q <= ~Q;
    //     endcase
    //     nQ <= ~Q;
    // end
endmodule  // issue


////////////////////////////////////////////////////////////////////////////////

module Problem_5_16_DFF (
    output A,
    B,
    input  x_in,
    clock,
    reset
);
    wire D_A, D_B;
    assign D_A = (~B & ~x_in) | (A & x_in);
    assign D_B = (B & x_in) | (A & ~x_in);
    DFF FF1 (
        A,
        nA,
        D_A,
        clock,
        reset
    );
    DFF FF2 (
        B,
        nB,
        D_B,
        clock,
        reset
    );
endmodule  // DONW


module Problem_5_16_TFF (
    output A,
    B,
    input  x_in,
    clock,
    reset
);
    wire FA, FB;  // FIX HERE
    // reg A, nA, B, nB; // ---------- no need of wire nA, nB
    assign FA = ~x_in & !(A ^ B);
    assign FB = ~x_in & (A ^ B);

    // Note: I havn't considered t_reset here

    TFF_with_DFF T1 (
        A,
        nA,
        FA,  // --------- mistake here
        clock,
        reset
    );
    TFF_with_DFF T2 (
        B,
        nB,
        FB,
        clock,
        reset
    );
endmodule  // DONE

module Problem_5_16_JK (
    output A,
    B,
    input  x,
    clock,
    reset
);
    wire ja, ka, jb, kb;

    assign ja = ~B & ~x;
    assign ka = B & ~x;
    assign jb = A & ~x;
    assign kb = ~A & ~x;

    JK_FF FF_A (
        A,
        nA,
        ja,
        ka,
        clock,
        reset
    );
    JK_FF FF_B (
        B,
        nB,
        jb,
        kb,
        clock,
        reset
    );
endmodule  // ISSUE

//////////////////////////////////////////////////////////////////////

module t_Problem_5_16_n;
    reg t_x_in, t_clock, t_reset;
    wire [1:0] state;

    // Problem_5_16_TFF P (
    Problem_5_16_DFF P_DFF (
        // Problem_5_16_JK P_JK (
        FA,
        FB,
        t_x_in,
        t_clock,
        t_reset
    );
    assign state = {FA, FB};

    initial begin
        $dumpfile("t_Problem_5_16_n.vcd");
        $dumpvars(0, t_Problem_5_16_n);
    end
    initial #150 $finish;

    initial begin
        t_reset = 1;
        repeat (2) #5 t_reset = ~t_reset;
    end

    initial begin
        #0 t_clock = 0;
        // repeat (28) #5 t_clock = ~t_clock;
        forever begin
            #5 t_clock = ~t_clock;
        end
    end

    initial begin
        #0 t_x_in = 0;
        #10 t_x_in = 1;
        repeat (3) #30 t_x_in = ~t_x_in;  // 30 th sec theke 3 bar repeat korbe
    end
endmodule

LabWork_LabAssignments/LabTest_13Nov/output/t_Problem_5_16_n.vcd
$date
	Tue Nov 19 00:48:13 2024
$end
$version
	Icarus Verilog
$end
$timescale
	1s
$end
$scope module t_Problem_5_16_n $end
$var wire 2 ! state [1:0] $end
$var wire 1 " FB $end
$var wire 1 # FA $end
$var reg 1 $ t_clock $end
$var reg 1 % t_reset $end
$var reg 1 & t_x_in $end
$scope module P_DFF $end
$var wire 1 ' D_A $end
$var wire 1 ( D_B $end
$var wire 1 $ clock $end
$var wire 1 % reset $end
$var wire 1 & x_in $end
$var wire 1 ) nB $end
$var wire 1 * nA $end
$var wire 1 " B $end
$var wire 1 # A $end
$scope module FF1 $end
$var wire 1 $ Clk $end
$var wire 1 ' D $end
$var wire 1 % rst $end
$var reg 1 # Q $end
$var reg 1 * nQ $end
$upscope $end
$scope module FF2 $end
$var wire 1 $ Clk $end
$var wire 1 ( D $end
$var wire 1 % rst $end
$var reg 1 " Q $end
$var reg 1 ) nQ $end
$upscope $end
$upscope $end
$upscope $end
$enddefinitions $end
$comment Show the parameter values. $end
$dumpall
$end
#0
$dumpvars
x*
x)
x(
x'
0&
1%
0$
x#
x"
bx !
$end
#5
1'
0(
1*
0#
1)
b0 !
0"
1$
0%
#10
0'
0$
1%
1&
#15
1$
#20
0$
#25
1$
#30
0$
#35
1$
#40
1'
0$
0&
#45
1(
b10 !
1#
1$
#50
0$
#55
0'
b11 !
1"
0*
1$
#60
0$
#65
0(
b1 !
0#
0)
1$
#70
1(
0$
1&
#75
1*
1$
#80
0$
#85
1$
#90
0$
#95
1$
#100
0(
0$
0&
#105
1'
b0 !
0"
1$
#110
0$
#115
1(
1)
b10 !
1#
1$
#120
0$
#125
0'
0*
b11 !
1"
1$
#130
0$
#135
0(
0)
b1 !
0#
1$
