LabWork_LabAssignments/LabTest_13Nov/t_Problem_5_16_new.v
// Kazi Rifat Morshed
// 230220

module DFF (
    output reg Q, nQ,
    input D, Clk, rst
);
    always @(posedge Clk or negedge rst) begin
        if (!rst) begin
            Q <= 1'b0;
            nQ <= 1'b1;
        end else begin
            Q <= D;
            nQ <= ~D;
        end
    end
endmodule

module TFF_with_DFF (
    output Q, nQ,
    input T, Clk, rst
);
    wire _T;
    assign _T = Q ^ T;
    DFF dff(Q, nQ, _T, Clk, rst);
endmodule

module Problem_5_16_n (
    output FA, FB,
    input x_in, clock, reset
);
    wire A, nA, B, nB;
    
    assign FA = ~x_in & !(A ^ B);
    assign FB = ~x_in & (A ^ B);

    TFF_with_DFF T1 (A, nA, x_in, clock, reset);
    TFF_with_DFF T2 (B, nB, x_in, clock, reset);

    assign state = {A, B};
endmodule

module t_Problem_5_16_n;
    reg t_x_in, t_clock, t_reset;
    wire FA, FB; // ---------------- absent in sir's code
    wire [1:0] state;
    
    Problem_5_16_n P (FA, FB, t_x_in, t_clock, t_reset);
    assign state = {FA, FB};
    
    initial begin
        $dumpfile("t_Problem_5_16_new.vcd");
        $dumpvars(0, t_Problem_5_16_n);
    end
    
    initial #150 $finish;
   
    initial begin 
        t_reset = 1;
        repeat (2)
            #5 t_reset = ~t_reset;  
    end
     
    initial begin 
        t_clock = 0;	      
        repeat (28)
            #5 t_clock = ~t_clock; 
    end
	
    initial begin
        t_x_in = 0;
        #10 t_x_in = 1;
        repeat (3)
            #30 t_x_in = ~t_x_in;
    end
endmodule

LabWork_LabAssignments/LabTest_13Nov/output/t_Problem_5_16_new.vcd
$date
	Wed Nov 13 16:26:36 2024
$end
$version
	Icarus Verilog
$end
$timescale
	1s
$end
$scope module t_Problem_5_16_n $end
$var wire 2 ! state [1:0] $end
$var wire 1 " FB $end
$var wire 1 # FA $end
$var reg 1 $ t_clock $end
$var reg 1 % t_reset $end
$var reg 1 & t_x_in $end
$scope module P $end
$var wire 1 # FA $end
$var wire 1 " FB $end
$var wire 1 $ clock $end
$var wire 1 % reset $end
$var wire 1 & x_in $end
$var wire 1 ' state $end
$var wire 1 ( nB $end
$var wire 1 ) nA $end
$var wire 1 * B $end
$var wire 1 + A $end
$scope module T1 $end
$var wire 1 $ Clk $end
$var wire 1 & T $end
$var wire 1 , _T $end
$var wire 1 % rst $end
$var wire 1 ) nQ $end
$var wire 1 + Q $end
$scope module dff $end
$var wire 1 $ Clk $end
$var wire 1 , D $end
$var wire 1 % rst $end
$var reg 1 + Q $end
$var reg 1 ) nQ $end
$upscope $end
$upscope $end
$scope module T2 $end
$var wire 1 $ Clk $end
$var wire 1 & T $end
$var wire 1 - _T $end
$var wire 1 % rst $end
$var wire 1 ( nQ $end
$var wire 1 * Q $end
$scope module dff $end
$var wire 1 $ Clk $end
$var wire 1 - D $end
$var wire 1 % rst $end
$var reg 1 * Q $end
$var reg 1 ( nQ $end
$upscope $end
$upscope $end
$upscope $end
$upscope $end
$enddefinitions $end
$comment Show the parameter values. $end
$dumpall
$end
#0
$dumpvars
x-
x,
x+
x*
x)
x(
x'
0&
1%
0$
x#
x"
bx !
$end
#5
0"
b10 !
1#
0,
0-
0'
1)
0+
1(
0*
1$
0%
#10
b0 !
0#
1,
1-
0$
1%
1&
#15
0-
1'
0,
0(
1*
0)
1+
1$
#20
0$
#25
1,
1-
0'
1)
0+
1(
0*
1$
#30
0$
#35
0-
1'
0,
0(
1*
0)
1+
1$
#40
b10 !
1#
1,
1-
0$
0&
#45
1$
#50
0$
#55
1$
#60
0$
#65
1$
#70
b0 !
0#
0,
0-
0$
1&
#75
1-
0'
1,
1(
0*
1)
0+
1$
#80
0$
#85
0,
0-
1'
0)
1+
0(
1*
1$
#90
0$
#95
1-
0'
1,
1(
0*
1)
0+
1$
#100
b10 !
1#
0,
0-
0$
0&
