LabWork_LabAssignments/Lab01/CT1_Q1_POS_SOP.v
module Canonical_POS (
    output Cano_POS,
    input  x,
    y,
    z
);
    assign Cano_POS = ((~x) | y | z) & ((~x) | y | (~z)) & (x | y | z);

endmodule

module Canonical_SOP (
    output Cano_SOP,
    input  x,
    y,
    z
);
    assign Cano_SOP = (x&y&z)|(x&y&(~z))|((~x)&y&z)|((~x)&y&(~z))|((~x)&(~y)&z);

endmodule

module CT1_Q1_POS_SOP;

    wire Cano_POS, Cano_SOP;
    reg x, y, z;

    Canonical_POS P (
        Cano_POS,
        x,
        y,
        z
    );
    Canonical_SOP S (
        Cano_SOP,
        x,
        y,
        z
    );

    initial begin
        $dumpfile("CT1_Q1_POS_SOP.vcd");
        $dumpvars(0, CT1_Q1_POS_SOP);

        x = 1'b0;
        y = 1'b0;
        z = 1'b0;
        #10 x = 1'b0;
        y = 1'b0;
        z = 1'b1;
        #10 x = 1'b0;
        y = 1'b1;
        z = 1'b0;
        #10 x = 1'b0;
        y = 1'b1;
        z = 1'b1;
        #10 x = 1'b1;
        y = 1'b0;
        z = 1'b0;
        #10 x = 1'b1;
        y = 1'b0;
        z = 1'b1;
        #10 x = 1'b1;
        y = 1'b1;
        z = 1'b0;
        #10 x = 1'b1;
        y = 1'b1;
        z = 1'b1;

    end
    initial #150 $finish;

endmodule

LabWork_LabAssignments/Lab01/output/CT1_Q1_POS_SOP.vcd
$date
	Mon Nov 18 23:17:04 2024
$end
$version
	Icarus Verilog
$end
$timescale
	1s
$end
$scope module CT1_Q1_POS_SOP $end
$var wire 1 ! Cano_SOP $end
$var wire 1 " Cano_POS $end
$var reg 1 # x $end
$var reg 1 $ y $end
$var reg 1 % z $end
$scope module P $end
$var wire 1 " Cano_POS $end
$var wire 1 # x $end
$var wire 1 $ y $end
$var wire 1 % z $end
$upscope $end
$scope module S $end
$var wire 1 ! Cano_SOP $end
$var wire 1 # x $end
$var wire 1 $ y $end
$var wire 1 % z $end
$upscope $end
$upscope $end
$enddefinitions $end
$comment Show the parameter values. $end
$dumpall
$end
#0
$dumpvars
0%
0$
0#
0"
0!
$end
#10
1"
1!
1%
#20
1!
0%
1$
#30
1%
#40
0!
0"
0%
0$
1#
#50
1%
#60
1!
1"
0%
1$
#70
1%
