LabWork_(incomplete_or_raugh)/Lab01/CT1Q1.v
module SOP (
    output FS,
    input x, y, z
);
    assign FS = y|(~x&z);
    
endmodule


module POS (
    output FP,
    input x, y, z
);
    assign FP = (!x|y)&(y|z);
    
endmodule


module t_CT1Q1;

    wire FSop, Fpop;
    reg x, y, z;
    SOP S (FSop, x, y, z);
    POS P (FPos, x, y, z);

    initial begin
        // $dumpfile("t_CT1Q1.vcd");
        $dumpfile("CT1Q1.vcd");
        $dumpvars(0, t_CT1Q1);
            x = 1'b0; y = 1'b0; z = 1'b0;    
        #10 x = 1'b0; y = 1'b0; z = 1'b1;    
        #10 x = 1'b0; y = 1'b1; z = 1'b0;    
        #10 x = 1'b0; y = 1'b1; z = 1'b1;    
        #10 x = 1'b1; y = 1'b0; z = 1'b0;    
        #10 x = 1'b1; y = 1'b0; z = 1'b1;    
        #10 x = 1'b1; y = 1'b1; z = 1'b0;    
        #10 x = 1'b1; y = 1'b1; z = 1'b1;    
    end

    initial #150 $finish;
    
endmodule

LabWork_LabAssignments/Lab01/output/CT1Q1.vcd
$date
	Fri Sep 20 19:30:10 2024
$end
$version
	Icarus Verilog
$end
$timescale
	1s
$end
$scope module t_CT1Q1 $end
$var wire 1 ! FSop $end
$var wire 1 " FPos $end
$var reg 1 # x $end
$var reg 1 $ y $end
$var reg 1 % z $end
$scope module P $end
$var wire 1 " FP $end
$var wire 1 # x $end
$var wire 1 $ y $end
$var wire 1 % z $end
$upscope $end
$scope module S $end
$var wire 1 ! FS $end
$var wire 1 # x $end
$var wire 1 $ y $end
$var wire 1 % z $end
$upscope $end
$upscope $end
$enddefinitions $end
$comment Show the parameter values. $end
$dumpall
$end
#0
$dumpvars
0%
0$
0#
0"
0!
$end
#10
1"
1!
1%
#20
0%
1$
#30
1%
#40
0!
0"
0%
0$
1#
#50
1%
#60
1"
1!
0%
1$
#70
1%
