Modules/wand_module.v
module wand_module (
    input A, B, C, D,
    output z, q
);
    wand p; // module parameter e dite pari nai
    wire x, y;

    assign x = A & B;
    assign y = C | D;
    
    // and g1(x, A, B);
    // difference between these two method ?!?!?!

    // or g2(y, C, D);

    // final output
    // and g3(z, x, y);
    assign z = x & y;
    

    // wand is a special net type, it needs to be assigned to multiple drivers
    // wand() // ei nam e kono gate nai, assign korete hobe
    assign p = x;
    assign p = y;
    assign q = p;
    
    
endmodule

module t_wand;
    wire p,z;
    reg A, B, C, D;

    // module instantiation
    wand_module uut(
        .A(A), .B(B), .C(C), .D(D),
        .q(q), .z(z)
    );

    initial begin
            $dumpfile("wand_module.vcd");
            $dumpvars(0, t_wand);            
        
                A = 1'b0; B = 1'b0; C = 1'b0; D = 1'b0;
            #10 A = 1'b0; B = 1'b0; C = 1'b0; D = 1'b1;
            #10 A = 1'b0; B = 1'b0; C = 1'b1; D = 1'b0;
            #10 A = 1'b0; B = 1'b0; C = 1'b1; D = 1'b1;
            #10 A = 1'b0; B = 1'b1; C = 1'b0; D = 1'b0;
            #10 A = 1'b0; B = 1'b1; C = 1'b0; D = 1'b1;
            #10 A = 1'b0; B = 1'b1; C = 1'b1; D = 1'b0;
            #10 A = 1'b0; B = 1'b1; C = 1'b1; D = 1'b1;
            #10 A = 1'b1; B = 1'b0; C = 1'b0; D = 1'b0;
            #10 A = 1'b1; B = 1'b0; C = 1'b0; D = 1'b1;
            #10 A = 1'b1; B = 1'b0; C = 1'b1; D = 1'b0;
            #10 A = 1'b1; B = 1'b0; C = 1'b1; D = 1'b1;
            #10 A = 1'b1; B = 1'b1; C = 1'b0; D = 1'b0;
            #10 A = 1'b1; B = 1'b1; C = 1'b0; D = 1'b1;
            #10 A = 1'b1; B = 1'b1; C = 1'b1; D = 1'b0;
            #10 A = 1'b1; B = 1'b1; C = 1'b1; D = 1'b1;

    end
    initial #200 $finish;
    
endmodule

Modules/output/wand_module.vcd
$date
	Fri Sep 20 12:00:43 2024
$end
$version
	Icarus Verilog
$end
$timescale
	1s
$end
$scope module t_wand $end
$var wire 1 ! z $end
$var wire 1 " q $end
$var reg 1 # A $end
$var reg 1 $ B $end
$var reg 1 % C $end
$var reg 1 & D $end
$scope module uut $end
$var wire 1 # A $end
$var wire 1 $ B $end
$var wire 1 % C $end
$var wire 1 & D $end
$var wire 1 ' p $end
$var wire 1 " q $end
$var wire 1 ( x $end
$var wire 1 ) y $end
$var wire 1 ! z $end
$upscope $end
$upscope $end
$enddefinitions $end
$comment Show the parameter values. $end
$dumpall
$end
#0
$dumpvars
0)
0(
0'
0&
0%
0$
0#
0"
0!
$end
#10
1)
1&
#20
0&
1%
#30
1&
#40
0)
0&
0%
1$
#50
1)
1&
#60
0&
1%
#70
1&
#80
0)
0&
0%
0$
1#
#90
1)
1&
#100
0&
1%
#110
1&
#120
0)
0"
0'
1(
0&
0%
1$
#130
1!
1"
1'
1)
1&
#140
0&
1%
#150
1&
